{
  "name": "Shortsword",
  "type": "weapon",
  "img": "./systems/twodsix/assets/icons/sword.svg",
  "system": {
    "name": "Sword",
    "techLevel": 1,
    "description": "A short, cut and thrust sword with a two-edged blade, 45-65 cm&nbsp;<span style=\"color: var(--s2d6-light-color); font-family: inherit; font-size: inherit; text-align: inherit;\">in length, often used in conjunction with a large shield. Also known as: gladius, xiphos,&nbsp;</span><span style=\"color: var(--s2d6-light-color); font-family: inherit; font-size: inherit; text-align: inherit;\">kindjal.</span>",
    "shortdescr": "Sword - melee",
    "quantity": 1,
    "weight": 1.2,
    "price": 90,
    "traits": [],
    "consumables": [],
    "skillModifier": 0,
    "skill": "",
    "associatedSkillName": "Melee Combat",
    "equipped": "equipped",
    "docReference": "",
    "pdfReference": {
      "type": "",
      "href": "",
      "label": ""
    },
    "target": {
      "value": null,
      "width": null,
      "units": "m",
      "type": "none"
    },
    "range": "0",
    "damage": "2d6+1",
    "damageBonus": 0,
    "magazineSize": 0,
    "ammo": 0,
    "useConsumableForAttack": "",
    "magazineCost": 0,
    "type": "weapon",
    "lawLevel": "8",
    "rangeBand": "personal",
    "weaponType": "melee",
    "damageType": "melee",
    "rateOfFire": "",
    "recoil": false,
    "features": "",
    "armorPiercing": 0,
    "handlingModifiers": "",
    "priorType": "unknown",
    "doubleTap": false,
    "parryAV": 14,
    "meleeRangeModifier": "0",
    "customCT": {
      "armor": {
        "nothing": "0",
        "jack": "0",
        "mesh": "0",
        "cloth": "0",
        "reflec": "0",
        "ablat": "0",
        "combat": "0"
      },
      "range": {
        "close": "0",
        "short": "0",
        "medium": "0",
        "long": "0",
        "veryLong": "0"
      }
    },
    "isShield": false
  },
  "effects": [],
  "folder": "crzJd4BeivxkkYsO",
  "flags": {
    "cf": {
      "id": "temp_d5gavafmlx",
      "path": "Cepheus Deluxe - Items#/CF_SEP/Weapons#/CF_SEP/Melee Weapons",
      "color": "#00aaaa"
    },
    "core": {},
    "twodsix": {}
  },
  "_stats": {
    "compendiumSource": "Compendium.twodsix.cepheus-light-items.isMChFZ3d57bfGu2",
    "duplicateSource": null,
    "coreVersion": "13.350",
    "systemId": "twodsix",
    "systemVersion": "6.8.1",
    "createdTime": 1727109554969,
    "modifiedTime": 1760016423000,
    "lastModifiedBy": "g35c71Hsyv7w1Lw4",
    "exportSource": null
  },
  "_id": "jbr0BTQZ9ozl46Bn",
  "sort": 0,
  "ownership": {
    "default": 0,
    "G0793twHyHfODmAJ": 3
  },
  "_key": "!items!jbr0BTQZ9ozl46Bn"
}
