{
  "name": "Hard to Kill",
  "type": "trait",
  "img": "systems/twodsix/assets/icons/heart-shield.svg",
  "system": {
    "docReference": "",
    "pdfReference": {
      "type": "",
      "href": "",
      "label": ""
    },
    "value": 0,
    "type": "trait",
    "description": "The character gains 5 additional Lifeblood points. This trait can be taken multiple times.",
    "prereq": "None",
    "shortdescr": "+5 Lifeblood per level",
    "subtype": "",
    "key": "key",
    "reference": ""
  },
  "effects": [],
  "folder": "Beuu5OH2jt6RvCOs",
  "sort": 3800000,
  "ownership": {
    "default": 0,
    "GOmBKof9PfoHZ54T": 3
  },
  "flags": {
    "twodsix": {},
    "cf": {
      "id": "temp_hyr6ua7dm4i",
      "path": "Cepheus Deluxe - Items#/CF_SEP/Traits",
      "color": "#00aaaa"
    }
  },
  "_id": "TnoPwKjU7UcfbD34",
  "_stats": {
    "systemId": "twodsix",
    "systemVersion": "6.8.1",
    "coreVersion": "13.350",
    "createdTime": 1732026737442,
    "modifiedTime": 1760016422747,
    "lastModifiedBy": "g35c71Hsyv7w1Lw4",
    "compendiumSource": null,
    "duplicateSource": null,
    "exportSource": null
  },
  "_key": "!items!TnoPwKjU7UcfbD34"
}
